sysdm/__init__.py
sysdm/__main__.py
sysdm/file_watcher.py
sysdm/flycheck_runner.py
sysdm/notify.py
sysdm/runner.py
sysdm/sysctl.py
sysdm/timer.py
sysdm/utils.py
sysdm/notifiers/__init__.py
sysdm/notifiers/base.py
sysdm-0.8.67.dist-info/METADATA
sysdm-0.8.67.dist-info/WHEEL
sysdm-0.8.67.dist-info/entry_points.txt
sysdm-0.8.67.dist-info/top_level.txt
sysdm-0.8.67.dist-info/RECORD
